<?xml version="1.0" encoding="UTF-8" standalone="no"?>
<Constraint version="1.0">
    <Name>alu_instr.action</Name>
    <Kind>FORMULA_BASED</Kind>
    <Description/>
    <Signature>
        <Variable name="alu_instr.action.block_0" type="LOGIC_BOOLEAN" value=""/>
        <Variable name="alu_instr.op1" type="(BIT_VECTOR 8)" value=""/>
        <Variable name="alu_instr.op2" type="(BIT_VECTOR 8)" value=""/>
        <Variable name="SRC1!2" type="(BIT_VECTOR 8)" value=""/>
        <Variable name="SRC2!2" type="(BIT_VECTOR 8)" value=""/>
    </Signature>
    <InnerRep>
        <Formula>
            <Operation family="ru.ispras.fortress.expression.StandardOperation" id="EQ">
                <VariableRef name="SRC1!2"/>
                <Operation family="ru.ispras.microtesk.translator.nml.coverage.SsaOperation" id="EXPAND">
                    <VariableRef name="alu_instr.op1"/>
                </Operation>
            </Operation>
        </Formula>
        <Formula>
            <Operation family="ru.ispras.fortress.expression.StandardOperation" id="EQ">
                <VariableRef name="SRC2!2"/>
                <Operation family="ru.ispras.microtesk.translator.nml.coverage.SsaOperation" id="EXPAND">
                    <VariableRef name="alu_instr.op2"/>
                </Operation>
            </Operation>
        </Formula>
        <Formula>
            <Operation family="ru.ispras.microtesk.translator.nml.coverage.SsaOperation" id="BLOCK">
                <VariableRef name="alu_instr.action.block_0"/>
                <Value type="LOGIC_BOOLEAN" value="true"/>
            </Operation>
        </Formula>
    </InnerRep>
</Constraint>
