<?xml version="1.0" encoding="UTF-8" standalone="no"?>
<Constraint version="1.0">
    <Name>and_r16r16.action.block_0</Name>
    <Kind>FORMULA_BASED</Kind>
    <Description/>
    <Signature>
        <Variable name="and_r16r16.action.block_1" type="LOGIC_BOOLEAN" value=""/>
    </Signature>
    <InnerRep>
        <Formula>
            <Operation family="ru.ispras.microtesk.translator.nml.coverage.SsaOperation" id="BLOCK">
                <VariableRef name="and_r16r16.action.block_1"/>
                <Value type="LOGIC_BOOLEAN" value="true"/>
            </Operation>
        </Formula>
    </InnerRep>
</Constraint>
